polygon_uploader/__init__.py
polygon_uploader/common/__init__.py
polygon_uploader/common/authentication.py
polygon_uploader/common/file_download.py
polygon_uploader/common/polygon.py
polygon_uploader/common/tmp_file_system.py
polygon_uploader/lojac/__init__.py
polygon_uploader/lojac/lojac.py
polygon_uploader/usaco/__init__.py
polygon_uploader/usaco/__main__.py
polygon_uploader/usaco/usaco.py
polygon_uploader-0.3.0.dist-info/LICENSE
polygon_uploader-0.3.0.dist-info/METADATA
polygon_uploader-0.3.0.dist-info/WHEEL
polygon_uploader-0.3.0.dist-info/entry_points.txt
polygon_uploader-0.3.0.dist-info/top_level.txt
polygon_uploader-0.3.0.dist-info/RECORD
