Metadata-Version: 2.1
Name: polygon-uploader
Version: 0.3.0
Summary: uploader to polygon.codeforces.com
Home-page: https://github.com/niyaznigmatullin/polygon-uploader
Author: Niyaz Nigmatullin
Classifier: Programming Language :: Python :: 3
Classifier: License :: OSI Approved :: MIT License
Classifier: Operating System :: OS Independent
License-File: LICENSE
Requires-Dist: polygon-api >=1.0a7
Requires-Dist: requests
Requires-Dist: pyyaml
Requires-Dist: progressbar2
Requires-Dist: beautifulsoup4
